setup.cfg
setup.py
woopra_tracker/__init__.py
woopra_tracker.egg-info/PKG-INFO
woopra_tracker.egg-info/SOURCES.txt
woopra_tracker.egg-info/dependency_links.txt
woopra_tracker.egg-info/top_level.txt