Metadata-Version: 1.0
Name: woopra-tracker
Version: 0.3
Summary: Woopra Analytics Tracking API
Home-page: https://github.com/Woopra/woopra-python-sdk
Author: Woopra
Author-email: dev@woopra.com
License: LICENSE.txt
Platform: UNKNOWN
